rpmlb/__init__.py
rpmlb/__main__.py
rpmlb/cli.py
rpmlb/custom.py
rpmlb/logging.py
rpmlb/recipe.py
rpmlb/utils.py
rpmlb/work.py
rpmlb/yaml.py
rpmlb/builder/__init__.py
rpmlb/builder/base.py
rpmlb/builder/copr.py
rpmlb/builder/custom.py
rpmlb/builder/dummy.py
rpmlb/builder/koji.py
rpmlb/builder/mock.py
rpmlb/downloader/__init__.py
rpmlb/downloader/base.py
rpmlb/downloader/base_rpkg.py
rpmlb/downloader/custom.py
rpmlb/downloader/fedpkg.py
rpmlb/downloader/local.py
rpmlb/downloader/none.py
rpmlb/downloader/rhpkg.py
rpmlb-1.1.1.dist-info/DESCRIPTION.rst
rpmlb-1.1.1.dist-info/METADATA
rpmlb-1.1.1.dist-info/RECORD
rpmlb-1.1.1.dist-info/WHEEL
rpmlb-1.1.1.dist-info/entry_points.txt
rpmlb-1.1.1.dist-info/metadata.json
rpmlb-1.1.1.dist-info/top_level.txt
