Metadata-Version: 2.0
Name: rpmlb
Version: 1.1.1
Summary: RPM List Builder
Home-page: https://github.com/sclorg/rpm-list-builder
Author: Jun Aruga
Author-email: jaruga@redhat.com
License: GPLv2+
Platform: UNKNOWN
Classifier: License :: OSI Approved :: GNU General Public License v2 or later (GPLv2+)
Classifier: Programming Language :: Python :: 3
Classifier: Programming Language :: Python :: 3.4
Classifier: Programming Language :: Python :: 3.5
Classifier: Programming Language :: Python :: 3.6
Classifier: Programming Language :: Python :: 3 :: Only
Requires-Dist: PyYAML
Requires-Dist: retry
Requires-Dist: click
Requires-Dist: typing
